basininflow/__init__.py
basininflow/cli.py
basininflow/inflow.py
basininflow-0.14.0.dist-info/METADATA
basininflow-0.14.0.dist-info/WHEEL
basininflow-0.14.0.dist-info/top_level.txt
basininflow-0.14.0.dist-info/RECORD
