Metadata-Version: 2.1
Name: basininflow
Version: 0.14.0
Summary: Calculates time series of runoff for basins from gridded runoff LSM data
Home-page: https://github.com/geoglows/basininflow
Author: Riley Hales PhD
Classifier: Programming Language :: Python
Classifier: Programming Language :: Python :: 3
Classifier: Programming Language :: Python :: 3.11
Classifier: Natural Language :: English
Classifier: Topic :: Scientific/Engineering
Classifier: Topic :: Scientific/Engineering :: Hydrology
Requires-Python: >=3
Requires-Dist: dask
Requires-Dist: netcdf4
Requires-Dist: numpy
Requires-Dist: pandas
Requires-Dist: psutil
Requires-Dist: pyarrow
Requires-Dist: pytest
Requires-Dist: xarray
